IgProfileClient/__init__.py
IgProfileClient/client.py
IgProfileClient/version.py
tests/__init__.py
tests/test_get_common_profile.py
ig_profile_client-0.0.1.dist-info/LICENSE.md
ig_profile_client-0.0.1.dist-info/METADATA
ig_profile_client-0.0.1.dist-info/WHEEL
ig_profile_client-0.0.1.dist-info/top_level.txt
ig_profile_client-0.0.1.dist-info/RECORD
