Metadata-Version: 2.1
Name: ig-profile-client
Version: 0.0.1
Summary: A common client to get instagram profile (public data)
Home-page: https://github.com/Panchorn/ig-profile-client.git
Author: Panchorn Lertvipada
Author-email: nonpcn@gmail.com
License: MIT
Platform: UNKNOWN
Classifier: Programming Language :: Python :: 3
Classifier: License :: OSI Approved :: MIT License
Classifier: Development Status :: 3 - Alpha
Requires-Dist: requests
